ramifier/__init__.py
ramifier/__main__.py
ramifier/backup.py
ramifier/config.py
ramifier/daemon.py
ramifier/global_settings.py
ramifier/interval.py
ramifier/lock.py
ramifier/log.py
ramifier/main.py
ramifier/runtime.py
ramifier/state.py
ramifier/target.py
ramifier/utils.py
ramifier/version.py
ramifier-0.5.1.dist-info/licenses/LICENSE
ramifier-0.5.1.dist-info/METADATA
ramifier-0.5.1.dist-info/WHEEL
ramifier-0.5.1.dist-info/entry_points.txt
ramifier-0.5.1.dist-info/top_level.txt
ramifier-0.5.1.dist-info/RECORD
