Metadata-Version: 2.4
Name: ramifier
Version: 0.5.1
Summary: RAM-accelerated directory manager with automatic backups
License-Expression: GPL-3.0-or-later
Requires-Python: >=3.9
License-File: LICENSE
Requires-Dist: pyyaml
Requires-Dist: psutil
Requires-Dist: pyxdg
Requires-Dist: zstandard
Dynamic: license-file
